{"py.test": [1, "/categories/pytest.html", {"posts": [{"date": "05/08/2014", "title": "Combining py.test and Selenium", "url": "/posts/combining-pytest-and-selenium.html", "isodate": "2014-05-08T21:13:56+00:00"}]}], "testing": [1, "/categories/testing.html", {"posts": [{"date": "05/08/2014", "title": "Combining py.test and Selenium", "url": "/posts/combining-pytest-and-selenium.html", "isodate": "2014-05-08T21:13:56+00:00"}]}], "selenium": [1, "/categories/selenium.html", {"posts": [{"date": "05/08/2014", "title": "Combining py.test and Selenium", "url": "/posts/combining-pytest-and-selenium.html", "isodate": "2014-05-08T21:13:56+00:00"}]}]}